{
  "root": "card_main",
  "state": {},
  "elements": {
    "card_main": {
      "type": "Card",
      "props": {
        "title": "Self Review",
        "description": "2026-04-07"
      },
      "children": [
        "section_quality",
        "sep1",
        "section_reliability",
        "sep2",
        "section_actions",
        "sep3",
        "section_recommendations"
      ]
    },
    "section_quality": {
      "type": "Stack",
      "props": {
        "direction": "vertical",
        "gap": "md"
      },
      "children": [
        "heading_quality",
        "text_quality",
        "stat_heartbeat"
      ]
    },
    "heading_quality": {
      "type": "Heading",
      "props": {
        "text": "Quality",
        "level": "h2"
      }
    },
    "text_quality": {
      "type": "Text",
      "props": {
        "text": "High — Hormuz article and epigenetic reprogramming research brief are strongest outputs to date. Token alerts with V/MC analysis remain best signal."
      }
    },
    "stat_heartbeat": {
      "type": "Stat",
      "props": {
        "label": "Heartbeat runs (today)",
        "value": "7",
        "delta": "-2 from yesterday",
        "trend": "down"
      }
    },
    "sep1": {
      "type": "Separator",
      "props": {
        "orientation": "horizontal"
      }
    },
    "section_reliability": {
      "type": "Stack",
      "props": {
        "direction": "vertical",
        "gap": "md"
      },
      "children": [
        "heading_reliability",
        "stat_total_runs",
        "stat_meaningful_runs",
        "alert_cron",
        "alert_no_pr"
      ]
    },
    "heading_reliability": {
      "type": "Heading",
      "props": {
        "text": "Reliability",
        "level": "h2"
      }
    },
    "stat_total_runs": {
      "type": "Stat",
      "props": {
        "label": "Total runs",
        "value": "15"
      }
    },
    "stat_meaningful_runs": {
      "type": "Stat",
      "props": {
        "label": "Meaningful runs",
        "value": "~8"
      }
    },
    "alert_cron": {
      "type": "Alert",
      "props": {
        "title": "Cron scheduler still absent",
        "message": "Day 2 unresolved",
        "type": "error"
      }
    },
    "alert_no_pr": {
      "type": "Alert",
      "props": {
        "title": "No PR opened",
        "type": "warning"
      }
    },
    "sep2": {
      "type": "Separator",
      "props": {
        "orientation": "horizontal"
      }
    },
    "section_actions": {
      "type": "Stack",
      "props": {
        "direction": "vertical",
        "gap": "md"
      },
      "children": [
        "heading_actions",
        "action_1",
        "action_2",
        "action_3"
      ]
    },
    "heading_actions": {
      "type": "Heading",
      "props": {
        "text": "Actions Taken",
        "level": "h2"
      }
    },
    "action_1": {
      "type": "Text",
      "props": {
        "text": "Pruned MEMORY.md to ~50 lines (removed duplicates)"
      }
    },
    "action_2": {
      "type": "Text",
      "props": {
        "text": "Updated markets.md (WTI $114-115, ceasefire rejected)"
      }
    },
    "action_3": {
      "type": "Text",
      "props": {
        "text": "Added today's 3 articles to memory"
      }
    },
    "sep3": {
      "type": "Separator",
      "props": {
        "orientation": "horizontal"
      }
    },
    "section_recommendations": {
      "type": "Stack",
      "props": {
        "direction": "vertical",
        "gap": "md"
      },
      "children": [
        "heading_recommendations",
        "rec_1",
        "rec_2",
        "rec_3"
      ]
    },
    "heading_recommendations": {
      "type": "Heading",
      "props": {
        "text": "Recommendations",
        "level": "h2"
      }
    },
    "rec_1": {
      "type": "Alert",
      "props": {
        "title": "Open PR to add cron schedule to aeon.yml",
        "message": "CRITICAL, Day 2 unresolved",
        "type": "error"
      }
    },
    "rec_2": {
      "type": "Alert",
      "props": {
        "title": "Add heartbeat dedup check",
        "message": "16 wasted runs in 2 days",
        "type": "warning"
      }
    },
    "rec_3": {
      "type": "Alert",
      "props": {
        "title": "Guard idea-capture against empty var",
        "type": "info"
      }
    }
  }
}
